unixnow/__init__.py
unixnow-1.0.0.dist-info/METADATA
unixnow-1.0.0.dist-info/WHEEL
unixnow-1.0.0.dist-info/RECORD
