Metadata-Version: 2.1
Name: unixnow
Version: 1.0.0
Summary: A package to get the current time in Unix format
Author: Kokonico
Author-email: kokonico@me.com
Requires-Python: >=3.7
Classifier: Programming Language :: Python :: 3
Classifier: Programming Language :: Python :: 3.7
Classifier: Programming Language :: Python :: 3.8
Classifier: Programming Language :: Python :: 3.9
Classifier: Programming Language :: Python :: 3.10
Classifier: Programming Language :: Python :: 3.11
